{
  "MoveDuration": 35,
  "Name": "DFinish_0",
  "Hitboxes": [
    {
      "Damage": 103,
      "Angle": -70,
      "Launch": 7,
      "KbScaling": 4,
      "Origin": {
        "X": 0,
        "Y": 0
      },
      "Length": {
        "X": 25,
        "Y": 0
      },
      "Radius": 8,
      "AutoSwipe": false,
      "Enabled": false,
      "Priority": 5,
      "Part": 0,
      "Grounded": false,
      "Aerial": false,
      "Motion": {},
      "Activation": {
        "20": true,
        "23": false
      }
    }
  ],
  "AnimationFrames": {
    "0": 0,
    "20": 1
  },
  "LeadInto": 0,
  "Motion": null,
  "Sustain": 0.1,
  "CanTurn": null,
  "CanCancel": null,
  "Animation": {
    "NextAnim": "neutral",
    "AnimID": 3,
    "Frames": 2,
    "AutoAnimate": false,
    "Frame": 1
  }
}